<?xml version="1.0" encoding="UTF-8"?>
<objects serializationModel="Studio.02.01.00">
	<object class="AudioFile" id="{1a487e5e-32f4-462c-9495-00f401bfbd78}">
		<property name="assetPath">
			<value>Dry Fire 1.wav</value>
		</property>
		<property name="frequencyInKHz">
			<value>96</value>
		</property>
		<property name="channelCount">
			<value>2</value>
		</property>
		<property name="length">
			<value>0.25038541666666669</value>
		</property>
		<relationship name="masterAssetFolder">
			<destination>{70cd42f0-a8ab-4c80-979a-be12c4715e8d}</destination>
		</relationship>
	</object>
</objects>
